ajax_views/__init__.py
ajax_views/apps.py
ajax_views/decorators.py
ajax_views/helpers.py
ajax_views/logging.py
ajax_views/registry.py
ajax_views/templatetags/__init__.py
ajax_views/templatetags/ajax_views.py
ajax_views/urls.py
ajax_views/views.py
ajax_views-0.8.1.dist-info/LICENSE
ajax_views-0.8.1.dist-info/METADATA
ajax_views-0.8.1.dist-info/WHEEL
ajax_views-0.8.1.dist-info/RECORD
